apify_client/__init__.py
apify_client/_errors.py
apify_client/_http_client.py
apify_client/_logging.py
apify_client/_statistics.py
apify_client/_utils.py
apify_client/client.py
apify_client/consts.py
apify_client/py.typed
apify_client/clients/__init__.py
apify_client/clients/base/__init__.py
apify_client/clients/base/actor_job_base_client.py
apify_client/clients/base/base_client.py
apify_client/clients/base/resource_client.py
apify_client/clients/base/resource_collection_client.py
apify_client/clients/resource_clients/__init__.py
apify_client/clients/resource_clients/actor.py
apify_client/clients/resource_clients/actor_collection.py
apify_client/clients/resource_clients/actor_env_var.py
apify_client/clients/resource_clients/actor_env_var_collection.py
apify_client/clients/resource_clients/actor_version.py
apify_client/clients/resource_clients/actor_version_collection.py
apify_client/clients/resource_clients/build.py
apify_client/clients/resource_clients/build_collection.py
apify_client/clients/resource_clients/dataset.py
apify_client/clients/resource_clients/dataset_collection.py
apify_client/clients/resource_clients/key_value_store.py
apify_client/clients/resource_clients/key_value_store_collection.py
apify_client/clients/resource_clients/log.py
apify_client/clients/resource_clients/request_queue.py
apify_client/clients/resource_clients/request_queue_collection.py
apify_client/clients/resource_clients/run.py
apify_client/clients/resource_clients/run_collection.py
apify_client/clients/resource_clients/schedule.py
apify_client/clients/resource_clients/schedule_collection.py
apify_client/clients/resource_clients/store_collection.py
apify_client/clients/resource_clients/task.py
apify_client/clients/resource_clients/task_collection.py
apify_client/clients/resource_clients/user.py
apify_client/clients/resource_clients/webhook.py
apify_client/clients/resource_clients/webhook_collection.py
apify_client/clients/resource_clients/webhook_dispatch.py
apify_client-1.12.1.dist-info/METADATA
apify_client-1.12.1.dist-info/WHEEL
apify_client-1.12.1.dist-info/licenses/LICENSE
apify_client-1.12.1.dist-info/RECORD
